w5xde/__init__.py
w5xde/compression.py
w5xde/networking.py
w5xde/w5xde.py
w5xde/webui.py
w5xde-0.1.1.dist-info/METADATA
w5xde-0.1.1.dist-info/WHEEL
w5xde-0.1.1.dist-info/top_level.txt
w5xde-0.1.1.dist-info/RECORD
