Metadata-Version: 2.1
Name: w5xde
Version: 0.1.1
Summary: Distributed machine learning
Home-page: https://github.com/rndmcoolawsmgrbg/WIIIIIDE/tree/dev_package
Author: Mikus Sturmanis, Jordan Legg
Author-email: ilovevisualstudiocode@gmail.com
License: UNKNOWN
Platform: UNKNOWN
Requires-Python: >=3.8
Requires-Dist: torch
Requires-Dist: cryptography
Requires-Dist: transformers
Requires-Dist: dash
Requires-Dist: dash-bootstrap-components
Requires-Dist: plotly
Requires-Dist: lz4
